lunchboy/__init__.py
lunchboy/lunch_spider.py
lunchboy-0.2.data/scripts/lunch
lunchboy-0.2.data/scripts/menu
lunchboy-0.2.dist-info/DESCRIPTION.rst
lunchboy-0.2.dist-info/METADATA
lunchboy-0.2.dist-info/RECORD
lunchboy-0.2.dist-info/WHEEL
lunchboy-0.2.dist-info/metadata.json
lunchboy-0.2.dist-info/top_level.txt
